rheofit/__init__.py
rheofit/models.py
rheofit/rheodata.py
rheofit/visualization.py
rheofit-0.1.3.dist-info/LICENSE
rheofit-0.1.3.dist-info/WHEEL
rheofit-0.1.3.dist-info/METADATA
rheofit-0.1.3.dist-info/RECORD
