Metadata-Version: 2.1
Name: rheofit
Version: 0.1.3
Summary: Import and analyze rheological data
Author-email: Marco Caggioni <marco.caggioni@gmail.com>
Classifier: License :: OSI Approved :: MIT License
Requires-Dist: lmfit
Requires-Dist: xmltodict
Requires-Dist: emcee
Requires-Dist: corner
Requires-Dist: pybroom
Requires-Dist: xlrd
Requires-Dist: ipywidgets
Project-URL: Home, https://github.com/rheopy/rheofit
